advanced_askai/__init__.py
advanced_askai/api.py
advanced_askai/chatbot_config.py
advanced_askai/chatgpt.py
advanced_askai/cli.py
advanced_askai/constants.py
advanced_askai/internal_chat_session.py
advanced_askai/make_chatbot.py
advanced_askai/openaicfg.py
advanced_askai/parse_args.py
advanced_askai/prompt_input.py
advanced_askai/run_chat_query.py
advanced_askai/streams.py
advanced_askai/types.py
advanced_askai/util.py
advanced_askai/assets/example.txt
advanced_askai/wip/streaming_console.py
advanced_askai-1.0.2.dist-info/LICENSE
advanced_askai-1.0.2.dist-info/METADATA
advanced_askai-1.0.2.dist-info/WHEEL
advanced_askai-1.0.2.dist-info/entry_points.txt
advanced_askai-1.0.2.dist-info/top_level.txt
advanced_askai-1.0.2.dist-info/RECORD
