Metadata-Version: 2.1
Name: advanced-askai
Version: 1.0.2
Summary: askai questions on the command line
Home-page: https://github.com/zackees/askai
Maintainer: Zachary Vorhies
License: BSD 3-Clause License
Keywords: template-python-cmd
Classifier: Programming Language :: Python :: 3
Requires-Python: >=3.7
License-File: LICENSE
Requires-Dist: json5
Requires-Dist: tiktoken >=0.7.0
Requires-Dist: openai <=1.55.3,>=1.3.7
Requires-Dist: appdirs
Requires-Dist: consolemd
Requires-Dist: keyring
